zecmf/__init__.py
zecmf/app.py
zecmf/constants.py
zecmf/api/__init__.py
zecmf/api/schemas/__init__.py
zecmf/auth/__init__.py
zecmf/auth/decorators.py
zecmf/auth/jwt.py
zecmf/cli/__init__.py
zecmf/cli/commands.py
zecmf/clients/__init__.py
zecmf/clients/answering_machine.py
zecmf/clients/codebot.py
zecmf/clients/llm.py
zecmf/clients/llm_request_builder.py
zecmf/config/__init__.py
zecmf/config/base.py
zecmf/extensions/__init__.py
zecmf/extensions/cors.py
zecmf/extensions/database.py
zecmf/extensions/queue.py
zecmf/extensions/task_monitor.py
zecmf/migrations/README.template
zecmf/migrations/__init__.py
zecmf/migrations/alembic.ini.template
zecmf/migrations/env.py.template
zecmf/migrations/script.py.mako
zecmf/models/__init__.py
zecmf/models/task_monitoring.py
zecmf/services/schemas/__init__.py
zecmf/services/schemas/answering_machine.py
zecmf/services/schemas/client_requests.py
zecmf/services/schemas/codebot.py
zecmf/services/schemas/llm.py
zecmf/services/schemas/task_monitoring.py
zecmf-0.1.23.dist-info/METADATA
zecmf-0.1.23.dist-info/WHEEL
zecmf-0.1.23.dist-info/top_level.txt
zecmf-0.1.23.dist-info/RECORD
